MANIFEST.in
README.md
RELEASE-VERSION
setup.py
version.py
kvlayer/__init__.py
kvlayer/_abstract_storage.py
kvlayer/_accumulo.py
kvlayer/_cassandra.py
kvlayer/_cbor_proxy.py
kvlayer/_client.py
kvlayer/_decorators.py
kvlayer/_exceptions.py
kvlayer/_file_storage.py
kvlayer/_hbase.py
kvlayer/_local_memory.py
kvlayer/_postgres.py
kvlayer/_postgrest.py
kvlayer/_redis.py
kvlayer/_riak.py
kvlayer/_split_s3.py
kvlayer/_utils.py
kvlayer/config.py
kvlayer.egg-info/PKG-INFO
kvlayer.egg-info/SOURCES.txt
kvlayer.egg-info/dependency_links.txt
kvlayer.egg-info/entry_points.txt
kvlayer.egg-info/requires.txt
kvlayer.egg-info/top_level.txt
kvlayer/encoders/__init__.py
kvlayer/encoders/ascii_percent.py
kvlayer/encoders/base.py
kvlayer/encoders/packed.py
kvlayer/tests/__init__.py
kvlayer/tests/config_accumulo.yaml
kvlayer/tests/config_cassandra.yaml
kvlayer/tests/config_cborproxy.yaml
kvlayer/tests/config_filestorage.yaml
kvlayer/tests/config_hbase.yaml
kvlayer/tests/config_local.yaml
kvlayer/tests/config_postgres.yaml
kvlayer/tests/config_postgrest.yaml
kvlayer/tests/config_redis.yaml
kvlayer/tests/config_riak.yaml
kvlayer/tests/make_namespace.py
kvlayer/tests/performance.py
kvlayer/tests/run.py
kvlayer/tests/test_accumulo.py
kvlayer/tests/test_batch_size.py
kvlayer/tests/test_cassandra_token_range.py
kvlayer/tests/test_cli.py
kvlayer/tests/test_decorators.py
kvlayer/tests/test_file_storage.py
kvlayer/tests/test_interface.py
kvlayer/tests/test_local.py
kvlayer/tests/test_postgres.py
kvlayer/tests/test_stats.py